setup.py
auto_datahandler/__init__.py
auto_datahandler/__version__.py
auto_datahandler.egg-info/PKG-INFO
auto_datahandler.egg-info/SOURCES.txt
auto_datahandler.egg-info/dependency_links.txt
auto_datahandler.egg-info/top_level.txt
auto_datahandler/basement__/ContralSelenium.py
auto_datahandler/basement__/ContralerDatabase.py
auto_datahandler/basement__/ContralerDir.py
auto_datahandler/basement__/ContralerImg.py
auto_datahandler/basement__/ContralerTime.py
auto_datahandler/basement__/Download.py
auto_datahandler/basement__/Encode.py
auto_datahandler/basement__/Handler.py
auto_datahandler/basement__/IsCheck.py
auto_datahandler/basement__/Timer.py
auto_datahandler/basement__/Tools.py
auto_datahandler/basement__/__init__.py
auto_datahandler/basement__/universal/__init__.py
auto_datahandler/basement__/universal/u_javascript.py
auto_datahandler/basement__/universal/u_selenium.py
auto_datahandler/customFunction__/__init__.py
auto_datahandler/customFunction__/Cleaner/__init__.py
auto_datahandler/customFunction__/Cleaner/base_cleaner.py
auto_datahandler/customFunction__/Cleaner/cleaner_article.py
auto_datahandler/customFunction__/Cleaner/cleaner_comment.py
auto_datahandler/customFunction__/Cleaner/cleaner_paragraph.py
auto_datahandler/customFunction__/Cleaner/cleaner_title.py
auto_datahandler/customFunction__/Cleaner/cleaner_translated_articles.py
auto_datahandler/customFunction__/Contraler_selenium/__init__.py
auto_datahandler/customFunction__/Contraler_selenium/contraler_selenium.py
auto_datahandler/customFunction__/Cracker/__init__.py
auto_datahandler/customFunction__/Cracker/base_cracker.py
auto_datahandler/customFunction__/Cracker/base_slidercrack.py
auto_datahandler/customFunction__/Cracker/cracker_douyin.py
auto_datahandler/customFunction__/Cracker/slidercheck_douyin.py
auto_datahandler/customFunction__/Filter/__init__.py
auto_datahandler/customFunction__/Filter/base_filter.py
auto_datahandler/customFunction__/Filter/filter_comment.py
auto_datahandler/customFunction__/Filter/filter_image.py
auto_datahandler/customFunction__/Filter/filter_keyparagraph.py
auto_datahandler/customFunction__/Filter/filter_posted.py
